CHANGES.txt
DEPENDENCES.txt
README.txt
setup.py
src/ng/__init__.py
src/ng.site.addon.profile.egg-info/PKG-INFO
src/ng.site.addon.profile.egg-info/SOURCES.txt
src/ng.site.addon.profile.egg-info/dependency_links.txt
src/ng.site.addon.profile.egg-info/namespace_packages.txt
src/ng.site.addon.profile.egg-info/not-zip-safe
src/ng.site.addon.profile.egg-info/requires.txt
src/ng.site.addon.profile.egg-info/top_level.txt
src/ng/site/__init__.py
src/ng/site/addon/__init__.py
src/ng/site/addon/profile/__init__.py
src/ng/site/addon/profile/configure.zcml
src/ng/site/addon/profile/ng.site.addon.profile.txt
src/ng/site/addon/profile/breadcrumbadapter/__init__.py
src/ng/site/addon/profile/breadcrumbadapter/configure.zcml
src/ng/site/addon/profile/contain/__init__.py
src/ng/site/addon/profile/contain/configure.zcml
src/ng/site/addon/profile/etc/ng.site.addon.profile-configure.zcml
src/ng/site/addon/profile/install/__init__.py
src/ng/site/addon/profile/install/configure.zcml
src/ng/site/addon/profile/install/install_auth.py
src/ng/site/addon/profile/install/install_content.py
src/ng/site/addon/profile/install/install_index.py
src/ng/site/addon/profile/profileadapter/__init__.py
src/ng/site/addon/profile/profileadapter/configure.zcml
src/ng/site/addon/profile/profileadapter/interfaces.py
src/ng/site/addon/profile/profileadapter/profileadapter.py
src/ng/site/addon/profile/profilefactory/__init__.py
src/ng/site/addon/profile/profilefactory/configure.zcml
src/ng/site/addon/profile/profilefactory/interfaces.py
src/ng/site/addon/profile/profilefactory/profile.py
src/ng/site/addon/profile/profilefactory/browser/__init__.py
src/ng/site/addon/profile/profilefactory/browser/configure.zcml
src/ng/site/addon/profile/profilefactory/browser/profile.pt